main.py
setup.py
FermiNet_with_ECP.egg-info/PKG-INFO
FermiNet_with_ECP.egg-info/SOURCES.txt
FermiNet_with_ECP.egg-info/dependency_links.txt
FermiNet_with_ECP.egg-info/requires.txt
FermiNet_with_ECP.egg-info/top_level.txt